BIO_OPTM/GAPLay.ipynb
BIO_OPTM/GA_AgentTestBed.ipynb
BIO_OPTM/__init__.py
BIO_OPTM/setup.py
BIO_OPTM/GA_TOOLS/GA_AGENTS.py
BIO_OPTM/GA_TOOLS/GA_BenchMarks.py
BIO_OPTM/GA_TOOLS/GA_ENV.py
BIO_OPTM/GA_TOOLS/GA_OPTIMIZATION_Class Tester Alpha.ipynb
BIO_OPTM/GA_TOOLS/TPS With GA.ipynb
BIO_OPTM/GA_TOOLS/__init__.py
BIO_OPTM/GA_TOOLS/.ipynb_checkpoints/GA_OPTIMIZATION_Class Tester Alpha-checkpoint.ipynb
BIO_OPTM/GA_TOOLS/.ipynb_checkpoints/TPS With GA-checkpoint.ipynb
BIO_OPTM/PSO_TOOLS/__init__.py
bio_optm-0.1.9.dist-info/METADATA
bio_optm-0.1.9.dist-info/WHEEL
bio_optm-0.1.9.dist-info/licenses/LICENSE
bio_optm-0.1.9.dist-info/RECORD
